{
  "chunk_id": "1. Annual Report 2023-24_p40_text0",
  "text": "Page 40 of 85 \n \nAI-NEXUS \nFAST NUCES ACM-AI proudly organized its flagship event, AI-Nexus under the \nsupervision of faculty head ‘Dr. Muhammad Waqas’ and co-head ‘Sania Urooj’. It was a \nthree-day extravaganza from 28th November to 30th November, 2023 featuring guest \nspeaker sessions, workshops, and competitions. The theme, \"A Journey through AI \nLandscapes,\" guided participants on a comprehensive exploration of the latest \nadvancements in artificial intelligence. The workshops delved deep into the realms of \nmachine learning, neural networks, and cutting-edge applications. Crafted to ensure \nimmersive learning experiences, these workshops provided attendees with hands-on \nopportunities to engage with the latest AI technologies. Our Competitions Head designed \nthrilling challenges for each batch, challenging students' problem-solving abilities, coding \nskills, and innovative thinking. The stakes were high, with winners and runners-up securing \na share of the Rs. 100,000 prize pool. \n \nSession by AshreiTech \nAshreiTech, visited FAST NUCES Karachi to conduct an interactive session on “how to \nstart a career in Microsoft, cyber security and artificial intelligence”. The session was \nconducted on 23rd November 2023 at Main Auditorium. After the session, the team of \nAshreitech met with the senior management and showed interest in signing an MoU with \nFAST NUCES Karachi to develop stronger ties with the students of FAST. \n \nOpen House of Database Systems Course Project \nOn 7th December 2023, Think and Create Society organized an Open House event for the \nDatabase Systems course projects. This event witnessed an overwhelming participation of \naround 660 students who showcased their projects with utmost enthusiasm and dedication. \nThe event was a true celebration of innovation and creativity, as students came together to \ndemonstrate their prowess in database systems. The vibrant atmosphere was filled with the \nspirit of learning, reflecting the dedication of our students. The highlight of the evening was \nthe Certificate Distribution Ceremony, a momentous occasion graced by distinguished \nguests Prof. Dr. Zulfiqar Ali Memon, Dr. Farooque Hassan, and Dr. Abdul Aziz. Their \npresence added an extra layer of honor and prestige to the event, inspiring our students to \nstrive for excellence in their academic endeavors. Among the impressive array of projects \npresented, the jury had the challenging task of selecting the best projects for recognition. \nThese outstanding projects stood out for their innovation, technical proficiency, and \npractical applicability. The Certificate of Appreciation was awarded to the talented \nindividuals behind these exceptional projects, acknowledging their hard work and \ndedication. \n \nMath Olympiad & Integration Bee \nOn 1st December 2023, Think and Create Society organized Math Olympiad filled with \nvibrant mathematical enthusiasm and brilliant minds colliding to solve intricate problems \nand celebrate the beauty of numbers. Participants immersed themselves in a whirlwind of \nnumerical challenges, fostering an environment of curiosity, creativity, and perseverance. \nThe event was a testament to the spirit of mathematical inquiry and the camaraderie within \nour mathematical community. TnC Looks forward to continue to delve deeper into the \nfascinating world of mathematics and creativity.",
  "metadata": {
    "source": "1. Annual Report 2023-24.pdf",
    "page": 40,
    "type": "text",
    "length": 3369
  }
}