{
  "chunk_id": "1. Annual Report 2023-24_p3_text0",
  "text": "Page 3 of 85 \n \n \n \n \n \n \n \n \n \n \n \n \n \n \n \n \n \n \nPreamble \n \n \nAs we reflect on another year of growth and achievement, we proudly present the Annual \nReport for the National University of Computer and Emerging Sciences (FAST-NUCES). \nFounded as a Federally Chartered University in July 2000, FASTNUCES has emerged as a \npremier institution in Pakistan, distinguished by the quality and impact of its graduates in \nthe local software and technology sectors. With five modern campuses strategically located \nin Karachi, Lahore, Islamabad, Peshawar, and Chiniot-Faisalabad, fostering an inclusive \nenvironment with a vibrant community of female scholars. Our commitment to providing a \nworld-class educational experience is matched by our dedication to advancing research that \naddresses the pressing social, economic, and technological challenges facing our nation.  \n \n \nThis report highlights the significant strides we have made towards our vision of becoming \na globally recognized research University within the next decade. From groundbreaking \nresearch initiatives to innovative educational programs, we remain steadfast in our mission \nto empower our students and contribute meaningfully to Pakistan development. We invite \nyou to explore our achievements, challenges, and the promising future that lies ahead as we \ncontinue to elevate standards in higher education and research. \n \n \nDr Aftab Ahmad \nRector",
  "metadata": {
    "source": "1. Annual Report 2023-24.pdf",
    "page": 3,
    "type": "text",
    "length": 1416
  }
}